Inorder Processor/src/ALU.vhd
library IEEE;
use IEEE.STD_LOGIC_1164.ALL;
use work.CustomALU_pkg.ALL;

entity ALU is
    Port (
        A : in STD_LOGIC_VECTOR (7 downto 0);  -- 8-bit input A
        B : in STD_LOGIC_VECTOR (7 downto 0);  -- 8-bit input B
        sel : in STD_LOGIC_VECTOR (2 downto 0); -- 3-bit select input
        Result : out STD_LOGIC_VECTOR (7 downto 0); -- 8-bit output Result
        Zero : out STD_LOGIC                 -- Zero flag
    );
end ALU;

architecture Behavioral of ALU is
begin
    process(A, B, sel)
    variable temp_result : STD_LOGIC_VECTOR (7 downto 0);
    begin
        case sel is
            when "000" => -- ADD
                temp_result := add_8bit(A, B);
            when "001" => -- SUBTRACT
                temp_result := sub_8bit(A, B);
            when "010" => -- AND
                temp_result := and_8bit(A, B);
            when "011" => -- OR
                temp_result := or_8bit(A, B);
            when "100" => -- XOR
                temp_result := xor_8bit(A, B);
            when "101" => -- NOR
                temp_result := nor_8bit(A, B);
            when others =>
                temp_result := (others => '0');  -- Default case
        end case;

        Result <= temp_result; -- Assign result to output
        
        -- Set the Zero flag
        if temp_result = "00000000" then
            Zero <= '1';
        else
            Zero <= '0';
        end if;
    end process;
end Behavioral;

Inorder Processor/src/Processor.vhd
library IEEE;
use IEEE.STD_LOGIC_1164.ALL;
use ieee.numeric_std.all;

entity Processor is
    Port (
        clk : in STD_LOGIC;
        reset : in STD_LOGIC;
        data_out : in STD_LOGIC_VECTOR (7 downto 0);
        instr : in STD_LOGIC_VECTOR (31 downto 0);

        instr_addr : out STD_LOGIC_VECTOR (7 downto 0);
        data_addr : out STD_LOGIC_VECTOR (7 downto 0);
        data_in : out STD_LOGIC_VECTOR (7 downto 0);
        data_wr : out STD_LOGIC
    );
end Processor;

architecture Behavioral of Processor is
    component ALU
        Port (
            A : in STD_LOGIC_VECTOR (7 downto 0);
            B : in STD_LOGIC_VECTOR (7 downto 0);
            sel : in STD_LOGIC_VECTOR (2 downto 0);
            Result : out STD_LOGIC_VECTOR (7 downto 0);
            Zero : out STD_LOGIC
        );
    end component;

    signal PC : STD_LOGIC_VECTOR (7 downto 0) := (others => '0');
    signal Inst_Reg : STD_LOGIC_VECTOR (31 downto 0);
    signal Reg_A, Reg_B : STD_LOGIC_VECTOR (7 downto 0);
    signal ALU_Res : STD_LOGIC_VECTOR (7 downto 0);
    signal ALU_Ctrl : STD_LOGIC_VECTOR (2 downto 0);
    signal Zero_Flag : STD_LOGIC;

begin
    -- Fetch
    instr_addr <= PC;
    Inst_Reg <= instr;

    -- Decode
    process(Inst_Reg)
    begin
        case Inst_Reg(31 downto 29) is
            when "000" => ALU_Ctrl <= "000"; -- ADD
            when "001" => ALU_Ctrl <= "001"; -- SUB
            when "010" => ALU_Ctrl <= "010"; -- AND
            when "011" => ALU_Ctrl <= "011"; -- OR
            when "100" => ALU_Ctrl <= "100"; -- XOR
            when "101" => ALU_Ctrl <= "101"; -- NOR
            when "110" => ALU_Ctrl <= "110"; -- Store
            when others => ALU_Ctrl <= "111"; -- Invalid
        end case;

        Reg_A <= Inst_Reg(23 downto 16);
        Reg_B <= Inst_Reg(15 downto 8);
    end process;

    -- Execute
    ALU_Unit: ALU
        port map (
            A => Reg_A,
            B => Reg_B,
            sel => ALU_Ctrl,
            Result => ALU_Res,
            Zero => Zero_Flag
        );

    -- Memory Access
    data_addr <= Inst_Reg(15 downto 8);
    data_in <= Reg_A;
    data_wr <= '1' when ALU_Ctrl = "110" else '0'; --store inst

    process(clk, reset)
    begin
        if reset = '1' then
            PC <= (others => '0');
        elsif rising_edge(clk) then
            PC <= std_logic_vector(unsigned(PC) + 1);
        end if;
    end process;

end Behavioral;

Inorder Processor/tb/Processor_tb.vhd
-- Processor_tb.vhd
library IEEE;
use IEEE.STD_LOGIC_1164.ALL;
use IEEE.NUMERIC_STD.ALL;

entity Processor_tb is
end Processor_tb;

architecture Behavioral of Processor_tb is
    -- Component Declaration
    component Processor
        Port (
            clk : in STD_LOGIC;
            reset : in STD_LOGIC;
            instr_addr : out STD_LOGIC_VECTOR (7 downto 0);
            instr : in STD_LOGIC_VECTOR (31 downto 0);
            data_addr : out STD_LOGIC_VECTOR (7 downto 0);
            data_in : out STD_LOGIC_VECTOR (7 downto 0);
            data_out : in STD_LOGIC_VECTOR (7 downto 0);
            data_wr : out STD_LOGIC
        );
    end component;
    
    -- Test Signals
    signal clk : STD_LOGIC := '0';
    signal reset : STD_LOGIC := '0';
    signal instr_addr : STD_LOGIC_VECTOR (7 downto 0);
    signal instr : STD_LOGIC_VECTOR (31 downto 0);
    signal data_addr : STD_LOGIC_VECTOR (7 downto 0);
    signal data_in : STD_LOGIC_VECTOR (7 downto 0);
    signal data_out : STD_LOGIC_VECTOR (7 downto 0);
    signal data_wr : STD_LOGIC;
    
    -- Clock period definition
    constant CLK_PERIOD : time := 10 ns;
    
begin
    -- Instantiate the Unit Under Test (UUT)
    UUT: Processor port map (
        clk => clk,
        reset => reset,
        instr_addr => instr_addr,
        instr => instr,
        data_addr => data_addr,
        data_in => data_in,
        data_out => data_out,
        data_wr => data_wr
    );
    
    -- Clock process
    clk_process: process
    begin
        clk <= '0';
        wait for CLK_PERIOD/2;
        clk <= '1';
        wait for CLK_PERIOD/2;
    end process;
    
    -- Stimulus process
    stim_proc: process
    begin
        -- Initialize
        reset <= '1';
        data_out <= x"00";
        wait for CLK_PERIOD*2;
        
        -- Release reset
        reset <= '0';
        wait for CLK_PERIOD;
        
        -- Test ADD instruction
        instr <= "00000000" & x"FF" & x"01" & x"00"; -- ADD FF + 01
        wait for CLK_PERIOD;
        
        -- Test SUB instruction
        instr <= "00100000" & x"FF" & x"01" & x"00"; -- SUB FF - 01
        wait for CLK_PERIOD;
        
        -- Test AND instruction
        instr <= "01000000" & x"FF" & x"0F" & x"00"; -- AND FF & 0F
        wait for CLK_PERIOD;
        
        -- Test OR instruction
        instr <= "01100000" & x"F0" & x"0F" & x"00"; -- OR F0 | 0F
        wait for CLK_PERIOD;
        
        -- Test XOR instruction
        instr <= "10000000" & x"FF" & x"55" & x"00"; -- XOR FF ^ 55
        wait for CLK_PERIOD;
        
        -- Test NOR instruction
        instr <= "10100000" & x"FF" & x"00" & x"00"; -- NOR FF NOR 00
        wait for CLK_PERIOD;
        
        -- Wait for a few more cycles
        wait for CLK_PERIOD*4;
        
        -- Test reset again
        reset <= '1';
        wait for CLK_PERIOD*2;
        reset <= '0';
        
        wait;
    end process;
end Behavioral;

Inorder Processor/work/processor_tb.vcd
$date
  Sun Nov 17 15:28:56 2024
$end
$version
  GHDL v0
$end
$timescale
  1 fs
$end
$scope module standard $end
$upscope $end
$scope module std_logic_1164 $end
$upscope $end
$scope module numeric_std $end
$upscope $end
$scope module processor_tb $end
$var reg 1 ! clk $end
$var reg 1 " reset $end
$var reg 8 # instr_addr[7:0] $end
$var reg 32 $ instr[31:0] $end
$var reg 8 % data_addr[7:0] $end
$var reg 8 & data_in[7:0] $end
$var reg 8 ' data_out[7:0] $end
$var reg 1 ( data_wr $end
$scope module uut $end
$var reg 1 ) clk $end
$var reg 1 * reset $end
$var reg 8 + instr_addr[7:0] $end
$var reg 32 , instr[31:0] $end
$var reg 8 - data_addr[7:0] $end
$var reg 8 . data_in[7:0] $end
$var reg 8 / data_out[7:0] $end
$var reg 1 0 data_wr $end
$var reg 8 1 pc[7:0] $end
$var reg 32 2 inst_reg[31:0] $end
$var reg 8 3 reg_a[7:0] $end
$var reg 8 4 reg_b[7:0] $end
$var reg 8 5 alu_res[7:0] $end
$var reg 3 6 alu_ctrl[2:0] $end
$var reg 1 7 zero_flag $end
$scope module alu_unit $end
$upscope $end
$upscope $end
$upscope $end
$enddefinitions $end
#0
0!
1"
b00000000 #
bUUUUUUUUUUUUUUUUUUUUUUUUUUUUUUUU $
bUUUUUUUU %
bUUUUUUUU &
b00000000 '
0(
0)
1*
b00000000 +
bUUUUUUUUUUUUUUUUUUUUUUUUUUUUUUUU ,
bUUUUUUUU -
bUUUUUUUU .
b00000000 /
00
b00000000 1
bUUUUUUUUUUUUUUUUUUUUUUUUUUUUUUUU 2
bUUUUUUUU 3
bUUUUUUUU 4
bUUUUUUUU 5
b111 6
U7
#5000000
1!
1)
#10000000
0!
0)
#15000000
1!
1)
#20000000
0!
0"
0)
0*
#25000000
1!
b00000001 #
1)
b00000001 +
b00000001 1
#30000000
0!
b00000000111111110000000100000000 $
b00000001 &
1(
0)
b00000000111111110000000100000000 ,
b00000001 .
10
b00000000111111110000000100000000 2
b11111111 3
b00000001 4
b000 6
#35000000
1!
b00000010 #
1)
b00000010 +
b00000010 1
#40000000
0!
b00100000111111110000000100000000 $
0(
0)
b00100000111111110000000100000000 ,
00
b00100000111111110000000100000000 2
b001 6
#45000000
1!
b00000011 #
1)
b00000011 +
b00000011 1
#50000000
0!
b01000000111111110000111100000000 $
b00001111 &
0)
b01000000111111110000111100000000 ,
b00001111 .
b01000000111111110000111100000000 2
b00001111 4
b010 6
#55000000
1!
b00000100 #
1)
b00000100 +
b00000100 1
#60000000
0!
b01100000111100000000111100000000 $
0)
b01100000111100000000111100000000 ,
b01100000111100000000111100000000 2
b11110000 3
b011 6
#65000000
1!
b00000101 #
1)
b00000101 +
b00000101 1
#70000000
0!
b10000000111111110101010100000000 $
b01010101 &
0)
b10000000111111110101010100000000 ,
b01010101 .
b10000000111111110101010100000000 2
b11111111 3
b01010101 4
b100 6
#75000000
1!
b00000110 #
1)
b00000110 +
b00000110 1
#80000000
0!
b10100000111111110000000000000000 $
b00000000 &
0)
b10100000111111110000000000000000 ,
b00000000 .
b10100000111111110000000000000000 2
b00000000 4
b101 6
#85000000
1!
b00000111 #
1)
b00000111 +
b00000111 1
#90000000
0!
0)
#95000000
1!
b00001000 #
1)
b00001000 +
b00001000 1
#100000000
0!
0)
#105000000
1!
b00001001 #
1)
b00001001 +
b00001001 1
#110000000
0!
0)
#115000000
1!
b00001010 #
1)
b00001010 +
b00001010 1
#120000000
0!
0)
#125000000
1!
b00001011 #
1)
b00001011 +
b00001011 1
#130000000
0!
1"
b00000000 #
0)
1*
b00000000 +
b00000000 1
#135000000
1!
1)
#140000000
0!
0)
#145000000
1!
1)
#150000000
0!
0"
0)
0*
#155000000
1!
b00000001 #
1)
b00000001 +
b00000001 1
#160000000
0!
0)
#165000000
1!
b00000010 #
1)
b00000010 +
b00000010 1
#170000000
0!
0)
#175000000
1!
b00000011 #
1)
b00000011 +
b00000011 1
#180000000
0!
0)
#185000000
1!
b00000100 #
1)
b00000100 +
b00000100 1
#190000000
0!
0)
#195000000
1!
b00000101 #
1)
b00000101 +
b00000101 1
