Inorder Processor/src/ALU.vhd
library IEEE;
use IEEE.STD_LOGIC_1164.ALL;
use work.CustomALU_pkg.ALL;

entity ALU is
    Port (
        A : in STD_LOGIC_VECTOR (7 downto 0);  -- 8-bit input A
        B : in STD_LOGIC_VECTOR (7 downto 0);  -- 8-bit input B
        sel : in STD_LOGIC_VECTOR (2 downto 0); -- 3-bit select input
        Result : out STD_LOGIC_VECTOR (7 downto 0); -- 8-bit output Result
        Zero : out STD_LOGIC                 -- Zero flag
    );
end ALU;

architecture Behavioral of ALU is
begin
    process(A, B, sel)
    variable temp_result : STD_LOGIC_VECTOR (7 downto 0);
    begin
        case sel is
            when "000" => -- ADD
                temp_result := add_8bit(A, B);
            when "001" => -- SUBTRACT
                temp_result := sub_8bit(A, B);
            when "010" => -- AND
                temp_result := and_8bit(A, B);
            when "011" => -- OR
                temp_result := or_8bit(A, B);
            when "100" => -- XOR
                temp_result := xor_8bit(A, B);
            when "101" => -- NOR
                temp_result := nor_8bit(A, B);
            when others =>
                temp_result := (others => '0');  -- Default case
        end case;

        Result <= temp_result; -- Assign result to output
        
        -- Set the Zero flag
        if temp_result = "00000000" then
            Zero <= '1';
        else
            Zero <= '0';
        end if;
    end process;
end Behavioral;

ALU/ALU_tb.vhd
library IEEE;
use IEEE.STD_LOGIC_1164.ALL;
use IEEE.NUMERIC_STD.ALL;  
use work.CustomALU_pkg.ALL;

entity ALU_tb is
end ALU_tb;

architecture Behavioral of ALU_tb is
    -- Component Declaration
    component ALU
        Port (
            A : in STD_LOGIC_VECTOR (7 downto 0);
            B : in STD_LOGIC_VECTOR (7 downto 0);
            sel : in STD_LOGIC_VECTOR (2 downto 0);
            Result : out STD_LOGIC_VECTOR (7 downto 0);
            Zero : out STD_LOGIC
        );
    end component;
    
    -- Test Signals
    signal A_tb      : STD_LOGIC_VECTOR (7 downto 0) := (others => '0');
    signal B_tb      : STD_LOGIC_VECTOR (7 downto 0) := (others => '0');
    signal sel_tb    : STD_LOGIC_VECTOR (2 downto 0) := (others => '0');
    signal Result_tb : STD_LOGIC_VECTOR (7 downto 0);
    signal Zero_tb   : STD_LOGIC;
    
    -- Helper procedure for printing test results
    procedure print_test_case(
        test_name: string;
        A, B: STD_LOGIC_VECTOR(7 downto 0);
        sel: STD_LOGIC_VECTOR(2 downto 0);
        result: STD_LOGIC_VECTOR(7 downto 0)) is
    begin
        report "Test: " & test_name & 
               " | A=" & integer'image(to_integer(unsigned(A))) &
               " | B=" & integer'image(to_integer(unsigned(B))) &
               " | Result=" & integer'image(to_integer(unsigned(result)));
    end procedure;
    
begin
    -- Unit Under Test (UUT)
    UUT: ALU port map (
        A => A_tb,
        B => B_tb,
        sel => sel_tb,
        Result => Result_tb,
        Zero => Zero_tb
    );
    
    -- Stimulus Process
    stim_proc: process
    begin
        -- Wait for 10ns for global reset
        wait for 10 ns;
        
        -- Test Case 1: Addition (000)
        A_tb <= "00000101";  -- 5
        B_tb <= "00000011";  -- 3
        sel_tb <= "000";     -- ADD
        wait for 10 ns;
        print_test_case("Addition", A_tb, B_tb, sel_tb, Result_tb);
        wait for 3 fs;
            
        -- Test Case 2: Subtraction (001)
        A_tb <= "00001000";  -- 8
        B_tb <= "00000011";  -- 3
        sel_tb <= "001";     -- SUB
        wait for 10 ns;
        print_test_case("Subtraction", A_tb, B_tb, sel_tb, Result_tb);
        wait for 3 fs;
            
        -- Test Case 3: AND (010)
        A_tb <= "11110000";
        B_tb <= "00001111";
        sel_tb <= "010";     -- AND
        wait for 10 ns;
        print_test_case("AND", A_tb, B_tb, sel_tb, Result_tb);
        wait for 3 fs;
            
        -- Test Case 4: OR (011)
        A_tb <= "11110000";
        B_tb <= "00001111";
        sel_tb <= "011";     -- OR
        wait for 10 ns;
        print_test_case("OR", A_tb, B_tb, sel_tb, Result_tb);
        wait for 3 fs;
            
        -- Test Case 5: XOR (100)
        A_tb <= "11110000";
        B_tb <= "00001111";
        sel_tb <= "100";     -- XOR
        wait for 10 ns;
        print_test_case("XOR", A_tb, B_tb, sel_tb, Result_tb);
        wait for 3 fs;
            
        -- Test Case 6: NOR (101)
        A_tb <= "11110000";
        B_tb <= "00001111";
        sel_tb <= "101";     -- NOR
        wait for 10 ns;
        print_test_case("NOR", A_tb, B_tb, sel_tb, Result_tb);
        wait for 3 fs;
            
        -- Test Case 7: Zero flag test
        A_tb <= "00000000";
        B_tb <= "00000000";
        sel_tb <= "000";     -- ADD
        wait for 10 ns;
        print_test_case("Zero Flag", A_tb, B_tb, sel_tb, Result_tb);
        wait for 3 fs;
            
        -- Test Case 8: Carry operation
        A_tb <= "11111111";
        B_tb <= "11111111";
        sel_tb <= "111";     -- Carry operation
        wait for 10 ns;
        print_test_case("Carry Op", A_tb, B_tb, sel_tb, Result_tb);
        wait for 3 fs;
        
        -- End simulation
        report "Simulation completed successfully";
        wait;
    end process;
    
end Behavioral;

ALU/ALU_tb.vcd
$date
  Sun Nov 10 19:26:29 2024
$end
$version
  GHDL v0
$end
$timescale
  1 fs
$end
$scope module standard $end
$upscope $end
$scope module std_logic_1164 $end
$upscope $end
$scope module numeric_std $end
$upscope $end
$scope module customalu_pkg $end
$upscope $end
$scope module alu_tb $end
$var reg 8 ! a_tb[7:0] $end
$var reg 8 " b_tb[7:0] $end
$var reg 3 # sel_tb[2:0] $end
$var reg 8 $ result_tb[7:0] $end
$var reg 1 % zero_tb $end
$scope module uut $end
$var reg 8 & a[7:0] $end
$var reg 8 ' b[7:0] $end
$var reg 3 ( sel[2:0] $end
$var reg 8 ) result[7:0] $end
$var reg 1 * zero $end
$upscope $end
$upscope $end
$enddefinitions $end
#0
b00000101 !
b00000011 "
b000 #
b00001000 $
0%
b00000101 &
b00000011 '
b000 (
b00001000 )
0*
#10000000
#10000003
b00001000 !
b001 #
b00000101 $
b00001000 &
b001 (
b00000101 )
#20000003
#20000006
b11110000 !
b00001111 "
b010 #
b00000000 $
1%
b11110000 &
b00001111 '
b010 (
b00000000 )
1*
#30000006
#30000009
b011 #
b11111111 $
0%
b011 (
b11111111 )
0*
#40000009
#40000012
b100 #
b100 (
#50000012
#50000015
b101 #
b00000000 $
1%
b101 (
b00000000 )
1*
#60000015
#60000018
b00000000 !
b00000000 "
b000 #
b00000000 &
b00000000 '
b000 (
#70000018
#70000021
b11111111 !
b11111111 "
b111 #
b11111111 &
b11111111 '
b111 (
